Metadata-Version: 1.0
Name: tapir
Version: 1.0
Summary: Tally Approximations of Phylogenetic Informativeness Rapidly (TAPIR)
Home-page: http://github.com/faircloth-lab/tapir/
Author: Brant Faircloth, Jonathan Chang, Mike Alfaro
Author-email: brant.faircloth+tapir@gmail.com
License: http://www.opensource.org/licenses/BSD-3-Clause
Platform: UNKNOWN
Classifier: Development Status :: 4 - Beta
Classifier: Environment :: Console
Classifier: Operating System :: OS Independent
Classifier: Intended Audience :: Science/Research
Classifier: License :: OSI Approved :: BSD License
Classifier: Programming Language :: Python
Classifier: Topic :: Scientific/Engineering :: Bio-Informatics
